trv-1.1.0.dist-info/DESCRIPTION.rst
trv-1.1.0.dist-info/entry_points.txt
trv-1.1.0.dist-info/RECORD
trv-1.1.0.dist-info/metadata.json
trv-1.1.0.dist-info/METADATA
trv-1.1.0.dist-info/top_level.txt
trv-1.1.0.dist-info/WHEEL
trv/__init__.py
trv/app.py
trv/resources.py
trv/_model.py
trv/_view.py
